fastmcp_agents/__init__.py
fastmcp_agents/agent/curator.py
fastmcp_agents/agent/multi_step.py
fastmcp_agents/agent/single_step.py
fastmcp_agents/agent/extended/evaluator.py
fastmcp_agents/bundled/flows/triage-github-issue.yml
fastmcp_agents/bundled/servers/claude_claude-code-mcp/README.md
fastmcp_agents/bundled/servers/claude_claude-code-mcp/server.yml
fastmcp_agents/bundled/servers/cyanheads_git-mcp-server/README.md
fastmcp_agents/bundled/servers/cyanheads_git-mcp-server/server.yml
fastmcp_agents/bundled/servers/flow_code-agent/README.md
fastmcp_agents/bundled/servers/flow_code-agent/server.yml
fastmcp_agents/bundled/servers/flow_github-triage/README.md
fastmcp_agents/bundled/servers/flow_github-triage/server.yml
fastmcp_agents/bundled/servers/github_github-mcp-server/README.md
fastmcp_agents/bundled/servers/github_github-mcp-server/server.yml
fastmcp_agents/bundled/servers/mcp_git/README.md
fastmcp_agents/bundled/servers/mcp_git/server.yml
fastmcp_agents/bundled/servers/motherduckdb_mcp-server-motherduck/README.md
fastmcp_agents/bundled/servers/motherduckdb_mcp-server-motherduck/server.yml
fastmcp_agents/bundled/servers/nickclyde_duckduckgo-mcp-server/README.md
fastmcp_agents/bundled/servers/nickclyde_duckduckgo-mcp-server/server.yml
fastmcp_agents/bundled/servers/strawgate_aider-wrapper-mcp/README.md
fastmcp_agents/bundled/servers/strawgate_aider-wrapper-mcp/server.yml
fastmcp_agents/bundled/servers/strawgate_filesystem-operations-mcp/README.md
fastmcp_agents/bundled/servers/strawgate_filesystem-operations-mcp/server.yml
fastmcp_agents/bundled/servers/wrale_mcp-server-tree-sitter/README.md
fastmcp_agents/bundled/servers/wrale_mcp-server-tree-sitter/server.yml
fastmcp_agents/cli/base.py
fastmcp_agents/cli/example.py
fastmcp_agents/cli/loader.py
fastmcp_agents/cli/models.py
fastmcp_agents/conversation/__init__.py
fastmcp_agents/conversation/types.py
fastmcp_agents/conversation/utils.py
fastmcp_agents/conversation/memory/base.py
fastmcp_agents-0.4.1.dist-info/METADATA
fastmcp_agents-0.4.1.dist-info/WHEEL
fastmcp_agents-0.4.1.dist-info/entry_points.txt
fastmcp_agents-0.4.1.dist-info/licenses/LICENSE
fastmcp_agents-0.4.1.dist-info/RECORD
