Metadata-Version: 2.4
Name: fastmcp-agents
Version: 0.4.1
Summary: Fastmcp Agents Project
License-File: LICENSE
Requires-Python: >=3.10
Requires-Dist: asyncclick>=8.1.8
Requires-Dist: fastmcp<=2.8.1
Requires-Dist: frozenlist==1.6.0
Requires-Dist: google-cloud-aiplatform>=1.94.0
Requires-Dist: google-genai>=1.16.1
Requires-Dist: jsonref>=1.1.0
Requires-Dist: litellm>=1.71.0
Requires-Dist: mcp>=1.9.0
Requires-Dist: numpydoc>=1.8.0
Requires-Dist: opentelemetry-api>=1.33.1
Requires-Dist: opentelemetry-exporter-otlp>=1.33.1
Requires-Dist: opentelemetry-sdk>=1.33.1
Requires-Dist: python-dotenv>=1.1.0
Requires-Dist: pyyaml>=6.0.2
